{
    "pae": 16.5,
    "iptm": 22.0,
    "pdockq": 0.023,
    "proA": "FBpp0071449",
    "proB": "FBpp0079565",
    "geneA": "CG9344",
    "geneB": "me31B",
    "annotationA": "RE43665p; Associated with the spliceosome snRNP U1, U2, U4/U6 and U5",
    "annotationB": "Putative ATP-dependent RNA helicase me31b; Unwinds RNA in an ATP-dependent fashion (Potential). Involved in germ cell formation",
    "ppi": "no or low",
    "interfaceA_sel": [],
    "interfaceB_sel": [],
    "interfaceA": [],
    "interfaceB": []
}