{
    "pae": 10.1,
    "iptm": 17.2,
    "pdockq": 0.041,
    "proA": "FBpp0078918",
    "proB": "FBpp0086974",
    "geneA": "COX5B",
    "geneB": "ox",
    "annotationA": "Cytochrome-c oxidase activity. It is involved in the biological process described with: mitochondrial electron transport, cytochrome c to oxygen",
    "annotationB": "Cytochrome b-c1 complex subunit 9; This is a component of the ubiquinol-cytochrome c reductase complex (complex III or cytochrome b-c1 complex), which is part of the mitochondrial respiratory chain. This subunit interacts with cytochrome c1 (By similarity)",
    "ppi": "no or low",
    "interfaceA_sel": [
        {
            "struct_asym_id": "A",
            "start_residue_number": 95,
            "end_residue_number": 105,
            "representation": "ball-and-stick",
            "sideChain": false,
            "color": {
                "r": 247,
                "g": 171,
                "b": 0
            },
            "focus": true
        }
    ],
    "interfaceB_sel": [
        {
            "struct_asym_id": "B",
            "start_residue_number": 31,
            "end_residue_number": 31,
            "representation": "ball-and-stick",
            "sideChain": false,
            "color": {
                "r": 247,
                "g": 171,
                "b": 0
            },
            "focus": true
        },
        {
            "struct_asym_id": "B",
            "start_residue_number": 35,
            "end_residue_number": 39,
            "representation": "ball-and-stick",
            "sideChain": false,
            "color": {
                "r": 247,
                "g": 171,
                "b": 0
            },
            "focus": true
        }
    ],
    "interfaceA": [
        "95-105"
    ],
    "interfaceB": [
        "31-31",
        "35-39"
    ]
}