{
    "pae": 17.6,
    "iptm": 20.9,
    "pdockq": 0.023,
    "proA": "FBpp0071543",
    "proB": "FBpp0074239",
    "geneA": "Sgf29",
    "geneB": "CG6506",
    "annotationA": "SAGA-associated factor 29kDa, isoform A; Methylated histone binding; histone acetyltransferase activity. It is involved in the biological process described with: chromatin remodeling; histone acetylation",
    "annotationB": "annotation not available",
    "ppi": "no or low",
    "interfaceA_sel": [],
    "interfaceB_sel": [],
    "interfaceA": [],
    "interfaceB": []
}