{
    "pae": 15.5,
    "iptm": 28.5,
    "pdockq": 0.023,
    "proA": "FBpp0071700",
    "proB": "FBpp0291529",
    "geneA": "CG3045",
    "geneB": "CG4159",
    "annotationA": "Pseudouridine synthase activity; RNA binding; pseudouridylate synthase activity. It is involved in the biological process described with: pseudouridine synthesis",
    "annotationB": "Pseudouridine synthase activity; RNA binding; pseudouridylate synthase activity. It is involved in the biological process described with: pseudouridine synthesis",
    "ppi": "no or low",
    "interfaceA_sel": [],
    "interfaceB_sel": [],
    "interfaceA": [],
    "interfaceB": []
}