{
    "pae": 23.3,
    "iptm": 14.2,
    "pdockq": 0.023,
    "proA": "FBpp0071534",
    "proB": "FBpp0099685",
    "geneA": "EfSec",
    "geneB": "CG12788",
    "annotationA": "RE67487p; GTPase activity; translation elongation factor activity; GTP binding. It is involved in the biological process described with: translational elongation; translational readthrough",
    "annotationB": "annotation not available",
    "ppi": "no or low",
    "interfaceA_sel": [],
    "interfaceB_sel": [],
    "interfaceA": [],
    "interfaceB": []
}