{
    "pae": 13.4,
    "iptm": 38.5,
    "pdockq": 0.085,
    "proA": "FBpp0071449",
    "proB": "FBpp0075395",
    "geneA": "CG9344",
    "geneB": "Prp31",
    "annotationA": "RE43665p; Associated with the spliceosome snRNP U1, U2, U4/U6 and U5",
    "annotationB": "Prp31 is a splicing factor associated with U4/U6.U5 tri-snRNP. It plays important roles in pre-mRNA splicing and other steps of RNA processing. Prp31 is essential for photoreceptor development",
    "ppi": "no or low",
    "interfaceA_sel": [
        {
            "struct_asym_id": "A",
            "start_residue_number": 22,
            "end_residue_number": 22,
            "representation": "ball-and-stick",
            "sideChain": false,
            "color": {
                "r": 247,
                "g": 171,
                "b": 0
            },
            "focus": true
        },
        {
            "struct_asym_id": "A",
            "start_residue_number": 26,
            "end_residue_number": 29,
            "representation": "ball-and-stick",
            "sideChain": false,
            "color": {
                "r": 247,
                "g": 171,
                "b": 0
            },
            "focus": true
        },
        {
            "struct_asym_id": "A",
            "start_residue_number": 49,
            "end_residue_number": 51,
            "representation": "ball-and-stick",
            "sideChain": false,
            "color": {
                "r": 247,
                "g": 171,
                "b": 0
            },
            "focus": true
        },
        {
            "struct_asym_id": "A",
            "start_residue_number": 56,
            "end_residue_number": 61,
            "representation": "ball-and-stick",
            "sideChain": false,
            "color": {
                "r": 247,
                "g": 171,
                "b": 0
            },
            "focus": true
        },
        {
            "struct_asym_id": "A",
            "start_residue_number": 70,
            "end_residue_number": 73,
            "representation": "ball-and-stick",
            "sideChain": false,
            "color": {
                "r": 247,
                "g": 171,
                "b": 0
            },
            "focus": true
        }
    ],
    "interfaceB_sel": [
        {
            "struct_asym_id": "B",
            "start_residue_number": 353,
            "end_residue_number": 356,
            "representation": "ball-and-stick",
            "sideChain": false,
            "color": {
                "r": 247,
                "g": 171,
                "b": 0
            },
            "focus": true
        },
        {
            "struct_asym_id": "B",
            "start_residue_number": 381,
            "end_residue_number": 381,
            "representation": "ball-and-stick",
            "sideChain": false,
            "color": {
                "r": 247,
                "g": 171,
                "b": 0
            },
            "focus": true
        },
        {
            "struct_asym_id": "B",
            "start_residue_number": 385,
            "end_residue_number": 388,
            "representation": "ball-and-stick",
            "sideChain": false,
            "color": {
                "r": 247,
                "g": 171,
                "b": 0
            },
            "focus": true
        }
    ],
    "interfaceA": [
        "22-22",
        "26-29",
        "49-51",
        "56-61",
        "70-73"
    ],
    "interfaceB": [
        "353-356",
        "381-381",
        "385-388"
    ]
}