{
    "pae": 24.3,
    "iptm": 18.0,
    "pdockq": 0.023,
    "proA": "FBpp0087323",
    "proB": "FBpp0087461",
    "geneA": "nclb",
    "geneB": "CG1671",
    "annotationA": "No child left behind; Chromatin DNA binding. It is involved in the biological process described with: germ cell development; ovarian follicle cell development; regulation of gene expression; male germ-line stem cell maintenance; ovarian fusome organization; male gonad development",
    "annotationB": "LD47550p; It is involved in the biological process described with: rRNA processing; neurogenesis",
    "ppi": "no or low",
    "interfaceA_sel": [],
    "interfaceB_sel": [],
    "interfaceA": [],
    "interfaceB": []
}