{
    "pae": 17.8,
    "iptm": 24.9,
    "pdockq": 0.023,
    "proA": "FBpp0085483",
    "proB": "FBpp0288471",
    "geneA": "Vha16-1",
    "geneB": "Vha44",
    "annotationA": "V-type proton ATPase 16 kDa proteolipid subunit; Proton-conducting pore forming subunit of the membrane integral V0 complex of vacuolar ATPase. V-ATPase is responsible for acidifying a variety of intracellular compartments in eukaryotic cells",
    "annotationB": "V-type proton ATPase subunit C; Subunit of the peripheral V1 complex of vacuolar ATPase. Subunit C is necessary for the assembly of the catalytic sector of the enzyme and is likely to have a specific function in its catalytic activity. V-ATPase is responsible for acidifying a variety of intracellular compartments in eukaryotic cells",
    "ppi": "no or low",
    "interfaceA_sel": [],
    "interfaceB_sel": [],
    "interfaceA": [],
    "interfaceB": []
}