{
    "pae": 25.0,
    "iptm": 14.6,
    "pdockq": 0.023,
    "proA": "FBpp0084638",
    "proB": "FBpp0086749",
    "geneA": "BCAS2",
    "geneB": "fand",
    "annotationA": "LD24242p; It is involved in the biological process described with: mRNA splicing, via spliceosome; mRNA processing",
    "annotationB": "FI18620p1; It is involved in the biological process described with: phagocytosis; RNA splicing; regulation of alternative mRNA splicing, via spliceosome; mRNA splicing, via spliceosome",
    "ppi": "no or low",
    "interfaceA_sel": [],
    "interfaceB_sel": [],
    "interfaceA": [],
    "interfaceB": []
}