{
    "pae": 17.6,
    "iptm": 24.1,
    "pdockq": 0.023,
    "proA": "FBpp0072745",
    "proB": "FBpp0080062",
    "geneA": "HBS1",
    "geneB": "Ski6",
    "annotationA": "HBS1, isoform A; GTPase activity; translation release factor activity; GTP binding. It is involved in the biological process described with: translational termination; defense response to Gram-negative bacterium; positive regulation of innate immune response",
    "annotationB": "Ski6, isoform A; 3'-5'-exoribonuclease activity. It is involved in the biological process described with: regulation of gene expression",
    "ppi": "no or low",
    "interfaceA_sel": [],
    "interfaceB_sel": [],
    "interfaceA": [],
    "interfaceB": []
}