{
    "pae": 24.4,
    "iptm": 14.2,
    "pdockq": 0.023,
    "proA": "FBpp0072050",
    "proB": "FBpp0087038",
    "geneA": "Tal",
    "geneB": "CG8525",
    "annotationA": "Probable transaldolase; Transaldolase is important for the balance of metabolites in the pentose-phosphate pathway",
    "annotationB": "CG8525, isoform A; Deoxyribose-phosphate aldolase activity. It is involved in the biological process described with: deoxyribonucleotide catabolic process",
    "ppi": "no or low",
    "interfaceA_sel": [],
    "interfaceB_sel": [],
    "interfaceA": [],
    "interfaceB": []
}