{
    "pae": 9.8,
    "iptm": 40.1,
    "pdockq": 0.094,
    "proA": "FBpp0072249",
    "proB": "FBpp0078433",
    "geneA": "Fcp1",
    "geneB": "RpII18",
    "annotationA": "TFIIF-interacting CTD phosphatase, isoform A; CTD phosphatase activity. It is involved in the biological process described with: neurogenesis",
    "annotationB": "DNA-directed RNA polymerases I, II, and III subunit RPABC2; DNA-dependent RNA polymerases catalyze the transcription of DNA into RNA using the four ribonucleoside triphosphates as substrates. Common component of RNA polymerases I, II and III which synthesize ribosomal RNA precursors, mRNA precursors and many functional non-coding RNAs, and small RNAs, such as 5S rRNA and tRNAs, respectively. Pol II is the central component of the basal RNA polymerase II transcription machinery. Pols are composed of mobile elements that move relative to each other. In Pol II, RPB6 is part of the clamp e [...] ",
    "ppi": "no or low",
    "interfaceA_sel": [
        {
            "struct_asym_id": "A",
            "start_residue_number": 79,
            "end_residue_number": 79,
            "representation": "ball-and-stick",
            "sideChain": false,
            "color": {
                "r": 247,
                "g": 171,
                "b": 0
            },
            "focus": true
        },
        {
            "struct_asym_id": "A",
            "start_residue_number": 148,
            "end_residue_number": 159,
            "representation": "ball-and-stick",
            "sideChain": false,
            "color": {
                "r": 247,
                "g": 171,
                "b": 0
            },
            "focus": true
        },
        {
            "struct_asym_id": "A",
            "start_residue_number": 177,
            "end_residue_number": 184,
            "representation": "ball-and-stick",
            "sideChain": false,
            "color": {
                "r": 247,
                "g": 171,
                "b": 0
            },
            "focus": true
        },
        {
            "struct_asym_id": "A",
            "start_residue_number": 194,
            "end_residue_number": 194,
            "representation": "ball-and-stick",
            "sideChain": false,
            "color": {
                "r": 247,
                "g": 171,
                "b": 0
            },
            "focus": true
        },
        {
            "struct_asym_id": "A",
            "start_residue_number": 198,
            "end_residue_number": 198,
            "representation": "ball-and-stick",
            "sideChain": false,
            "color": {
                "r": 247,
                "g": 171,
                "b": 0
            },
            "focus": true
        },
        {
            "struct_asym_id": "A",
            "start_residue_number": 268,
            "end_residue_number": 268,
            "representation": "ball-and-stick",
            "sideChain": false,
            "color": {
                "r": 247,
                "g": 171,
                "b": 0
            },
            "focus": true
        },
        {
            "struct_asym_id": "A",
            "start_residue_number": 275,
            "end_residue_number": 275,
            "representation": "ball-and-stick",
            "sideChain": false,
            "color": {
                "r": 247,
                "g": 171,
                "b": 0
            },
            "focus": true
        }
    ],
    "interfaceB_sel": [
        {
            "struct_asym_id": "B",
            "start_residue_number": 62,
            "end_residue_number": 77,
            "representation": "ball-and-stick",
            "sideChain": false,
            "color": {
                "r": 247,
                "g": 171,
                "b": 0
            },
            "focus": true
        },
        {
            "struct_asym_id": "B",
            "start_residue_number": 91,
            "end_residue_number": 93,
            "representation": "ball-and-stick",
            "sideChain": false,
            "color": {
                "r": 247,
                "g": 171,
                "b": 0
            },
            "focus": true
        }
    ],
    "interfaceA": [
        "79-79",
        "148-159",
        "177-184",
        "194-194",
        "198-198",
        "268-268",
        "275-275"
    ],
    "interfaceB": [
        "62-77",
        "91-93"
    ]
}