{
    "pae": 0.8,
    "iptm": 81.5,
    "pdockq": 0.681,
    "proA": "FBpp0083354",
    "proB": "FBpp0085724",
    "geneA": "EloB",
    "geneB": "EloC",
    "annotationA": "Elongin B (EloB) is essential for development and participates in the control of wing cell identity. The EloB, EloC and EloA subunits of the Elongin complex interact in vivo with the chromatin factor corto",
    "annotationB": "Elongin C (EloC) is essential for development and participates in the control of wing cell identity. The EloC, EloB and EloA subunits of the Elongin complex interact in vivo with the chromatin factor corto; Belongs to the SKP1 family",
    "ppi": "high confidence",
    "interfaceA_sel": [
        {
            "struct_asym_id": "A",
            "start_residue_number": 2,
            "end_residue_number": 17,
            "representation": "ball-and-stick",
            "sideChain": false,
            "color": {
                "r": 247,
                "g": 171,
                "b": 0
            },
            "focus": true
        },
        {
            "struct_asym_id": "A",
            "start_residue_number": 26,
            "end_residue_number": 36,
            "representation": "ball-and-stick",
            "sideChain": false,
            "color": {
                "r": 247,
                "g": 171,
                "b": 0
            },
            "focus": true
        },
        {
            "struct_asym_id": "A",
            "start_residue_number": 69,
            "end_residue_number": 75,
            "representation": "ball-and-stick",
            "sideChain": false,
            "color": {
                "r": 247,
                "g": 171,
                "b": 0
            },
            "focus": true
        },
        {
            "struct_asym_id": "A",
            "start_residue_number": 93,
            "end_residue_number": 101,
            "representation": "ball-and-stick",
            "sideChain": false,
            "color": {
                "r": 247,
                "g": 171,
                "b": 0
            },
            "focus": true
        },
        {
            "struct_asym_id": "A",
            "start_residue_number": 105,
            "end_residue_number": 105,
            "representation": "ball-and-stick",
            "sideChain": false,
            "color": {
                "r": 247,
                "g": 171,
                "b": 0
            },
            "focus": true
        },
        {
            "struct_asym_id": "A",
            "start_residue_number": 109,
            "end_residue_number": 109,
            "representation": "ball-and-stick",
            "sideChain": false,
            "color": {
                "r": 247,
                "g": 171,
                "b": 0
            },
            "focus": true
        }
    ],
    "interfaceB_sel": [
        {
            "struct_asym_id": "B",
            "start_residue_number": 11,
            "end_residue_number": 17,
            "representation": "ball-and-stick",
            "sideChain": false,
            "color": {
                "r": 247,
                "g": 171,
                "b": 0
            },
            "focus": true
        },
        {
            "struct_asym_id": "B",
            "start_residue_number": 23,
            "end_residue_number": 23,
            "representation": "ball-and-stick",
            "sideChain": false,
            "color": {
                "r": 247,
                "g": 171,
                "b": 0
            },
            "focus": true
        },
        {
            "struct_asym_id": "B",
            "start_residue_number": 30,
            "end_residue_number": 40,
            "representation": "ball-and-stick",
            "sideChain": false,
            "color": {
                "r": 247,
                "g": 171,
                "b": 0
            },
            "focus": true
        },
        {
            "struct_asym_id": "B",
            "start_residue_number": 71,
            "end_residue_number": 88,
            "representation": "ball-and-stick",
            "sideChain": false,
            "color": {
                "r": 247,
                "g": 171,
                "b": 0
            },
            "focus": true
        },
        {
            "struct_asym_id": "B",
            "start_residue_number": 96,
            "end_residue_number": 107,
            "representation": "ball-and-stick",
            "sideChain": false,
            "color": {
                "r": 247,
                "g": 171,
                "b": 0
            },
            "focus": true
        }
    ],
    "interfaceA": [
        "2-17",
        "26-36",
        "69-75",
        "93-101",
        "105-105",
        "109-109"
    ],
    "interfaceB": [
        "11-17",
        "23-23",
        "30-40",
        "71-88",
        "96-107"
    ]
}