{
    "pae": 15.3,
    "iptm": 30.0,
    "pdockq": 0.023,
    "proA": "FBpp0073010",
    "proB": "FBpp0305117",
    "geneA": "Scsalpha",
    "geneB": "ATPsyndelta",
    "annotationA": "Succinate--CoA ligase [ADP/GDP-forming] subunit alpha, mitochondrial; Succinyl-CoA synthetase functions in the citric acid cycle (TCA), coupling the hydrolysis of succinyl-CoA to the synthesis of either ATP or GTP and thus represents the only step of substrate-level phosphorylation in the TCA. The alpha subunit of the enzyme binds the substrates coenzyme A and phosphate, while succinate binding and specificity for either ATP or GTP is provided by different beta subunits",
    "annotationB": "ATP synthase, delta subunit, isoform A; Proton-transporting ATP synthase activity, rotational mechanism; proton-transporting ATPase activity, rotational mechanism; hydrogen-exporting ATPase activity, phosphorylative mechanism. It is involved in the biological process described with: proton transport; ATP synthesis coupled proton transport",
    "ppi": "no or low",
    "interfaceA_sel": [],
    "interfaceB_sel": [],
    "interfaceA": [],
    "interfaceB": []
}