{
    "pae": 13.0,
    "iptm": 14.9,
    "pdockq": 0.026,
    "proA": "FBpp0073228",
    "proB": "FBpp0297136",
    "geneA": "ATPsynCF6L",
    "geneB": "ATPsynG",
    "annotationA": "ATP synthase, coupling factor 6-like; Hydrogen ion transmembrane transporter activity; hydrogen-exporting ATPase activity, phosphorylative mechanism. It is involved in the biological process described with: ATP synthesis coupled proton transport",
    "annotationB": "Hydrogen-exporting ATPase activity, phosphorylative mechanism. It is involved in the biological process described with: proton transport; ATP synthesis coupled proton transport",
    "ppi": "no or low",
    "interfaceA_sel": [
        {
            "struct_asym_id": "A",
            "start_residue_number": 29,
            "end_residue_number": 32,
            "representation": "ball-and-stick",
            "sideChain": false,
            "color": {
                "r": 247,
                "g": 171,
                "b": 0
            },
            "focus": true
        },
        {
            "struct_asym_id": "A",
            "start_residue_number": 36,
            "end_residue_number": 39,
            "representation": "ball-and-stick",
            "sideChain": false,
            "color": {
                "r": 247,
                "g": 171,
                "b": 0
            },
            "focus": true
        },
        {
            "struct_asym_id": "A",
            "start_residue_number": 59,
            "end_residue_number": 59,
            "representation": "ball-and-stick",
            "sideChain": false,
            "color": {
                "r": 247,
                "g": 171,
                "b": 0
            },
            "focus": true
        }
    ],
    "interfaceB_sel": [
        {
            "struct_asym_id": "B",
            "start_residue_number": 26,
            "end_residue_number": 26,
            "representation": "ball-and-stick",
            "sideChain": false,
            "color": {
                "r": 247,
                "g": 171,
                "b": 0
            },
            "focus": true
        },
        {
            "struct_asym_id": "B",
            "start_residue_number": 74,
            "end_residue_number": 74,
            "representation": "ball-and-stick",
            "sideChain": false,
            "color": {
                "r": 247,
                "g": 171,
                "b": 0
            },
            "focus": true
        },
        {
            "struct_asym_id": "B",
            "start_residue_number": 78,
            "end_residue_number": 78,
            "representation": "ball-and-stick",
            "sideChain": false,
            "color": {
                "r": 247,
                "g": 171,
                "b": 0
            },
            "focus": true
        },
        {
            "struct_asym_id": "B",
            "start_residue_number": 82,
            "end_residue_number": 82,
            "representation": "ball-and-stick",
            "sideChain": false,
            "color": {
                "r": 247,
                "g": 171,
                "b": 0
            },
            "focus": true
        }
    ],
    "interfaceA": [
        "29-32",
        "36-39",
        "59-59"
    ],
    "interfaceB": [
        "26-26",
        "74-74",
        "78-78",
        "82-82"
    ]
}